flask_resteasy.py
Flask_RESTeasy-0.0.8.dist-info/DESCRIPTION.rst
Flask_RESTeasy-0.0.8.dist-info/METADATA
Flask_RESTeasy-0.0.8.dist-info/RECORD
Flask_RESTeasy-0.0.8.dist-info/WHEEL
Flask_RESTeasy-0.0.8.dist-info/metadata.json
Flask_RESTeasy-0.0.8.dist-info/top_level.txt
