Metadata-Version: 2.0
Name: Flask-RESTeasy
Version: 0.0.8
Summary: Create easy REST APIs with Flask
Home-page: https://www.github.com/jidn/flask-resteasy/
Author: Clinton James
Author-email: clinton.james@anuit.com
License: Apache License 2.0
Download-URL: https://github.com/jidn/flask-resteasy/tarball/0.0.8
Keywords: flask,REST,json,MethodView
Platform: UNKNOWN
Classifier: Development Status :: 4 - Beta
Classifier: Framework :: Flask
Classifier: Intended Audience :: Developers
Classifier: Environment :: Web Environment
Classifier: License :: OSI Approved :: Apache Software License
Classifier: Programming Language :: Python
Classifier: Programming Language :: Python :: 2.7
Classifier: Programming Language :: Python :: 3
Classifier: Topic :: Internet :: WWW/HTTP :: Dynamic Content
Classifier: Topic :: Software Development :: Libraries :: Python Modules
Requires-Dist: Flask (>=0.10)
